examples/__init__.py
examples/chat_bot.py
examples/desktop_authenticator.py
examples/storehouse.py
steampy/__init__.py
steampy/chat.py
steampy/client.py
steampy/confirmation.py
steampy/exceptions.py
steampy/guard.py
steampy/login.py
steampy/market.py
steampy/models.py
steampy/utils.py
test/__init__.py
test/test_client.py
test/test_guard.py
test/test_market.py
test/test_utils.py
steampy_joki-0.76.dist-info/LICENSE.txt
steampy_joki-0.76.dist-info/METADATA
steampy_joki-0.76.dist-info/WHEEL
steampy_joki-0.76.dist-info/top_level.txt
steampy_joki-0.76.dist-info/RECORD
